[
  {
    "id": "moh7qo3ezkgo7",
    "invoiceNo": "INV-432",
    "customerName": "N THULASI",
    "customerCompany": "Union Bank of India  Mahanandi branch",
    "customerGstin": "37AAACU0564G2ZF",
    "customerPhone": "9346463784",
    "customerEmail": "",
    "billAddr1": "",
    "billAddr2": "",
    "billCity": "",
    "billState": "37",
    "billPin": "",
    "supplyCode": "37",
    "reference": "208",
    "checkIn": "2026-04-26",
    "checkInTime": "00:00",
    "checkOut": "2026-04-27",
    "checkOutTime": "00:00",
    "items": [
      {
        "id": "moh7qo3eytwho",
        "description": "ROOM SERVICE",
        "sac": "996322",
        "rate": 1000,
        "qty": 2,
        "unit": "DAY",
        "taxRate": 5
      }
    ],
    "notes": "",
    "status": "draft",
    "total": 2100
  },
  {
    "id": "moh7n9lehfjrt",
    "invoiceNo": "INV-431",
    "customerName": "MANGALI MADHU MOHAN",
    "customerCompany": "Union Bank of India dornipadu",
    "customerGstin": "37AAACU0564G2ZF",
    "customerPhone": "8247303486",
    "customerEmail": "",
    "billAddr1": "",
    "billAddr2": "",
    "billCity": "",
    "billState": "37",
    "billPin": "518135",
    "supplyCode": "37",
    "reference": "307",
    "checkIn": "2026-04-27",
    "checkInTime": "05:00",
    "checkOut": "2026-04-27",
    "checkOutTime": "19:00",
    "items": [
      {
        "id": "moh7n9lepybki",
        "description": "ROOM SERVICE",
        "sac": "996322",
        "rate": 1000,
        "qty": 1,
        "unit": "DAY",
        "taxRate": 5
      }
    ],
    "notes": "",
    "status": "draft",
    "total": 1050
  },
  {
    "id": "moh7j2ofm7nm5",
    "invoiceNo": "INV-430",
    "customerName": "B RAMALINGESWARA RAO",
    "customerCompany": "Union Bank of India bandi atmakur",
    "customerGstin": "37AAACU0564G2ZF",
    "customerPhone": "9959450981",
    "customerEmail": "",
    "billAddr1": "",
    "billAddr2": "",
    "billCity": "",
    "billState": "37",
    "billPin": "518523",
    "supplyCode": "37",
    "reference": "304",
    "checkIn": "2026-04-27",
    "checkInTime": "05:00",
    "checkOut": "2026-04-27",
    "checkOutTime": "19:00",
    "items": [
      {
        "id": "moh7j2ofcfre2",
        "description": "ROOM SERVICE",
        "sac": "996322",
        "rate": 1000,
        "qty": 1,
        "unit": "DAY",
        "taxRate": 5
      }
    ],
    "notes": "",
    "status": "draft",
    "total": 1050
  },
  {
    "id": "moh7dcmznvp9h",
    "invoiceNo": "INV-429",
    "customerName": "CHAKALI NAGESWARA RAO",
    "customerCompany": "Union Bank of India palkor",
    "customerGstin": "37AAACU0564G2ZF",
    "customerPhone": "7382263497",
    "customerEmail": "",
    "billAddr1": "",
    "billAddr2": "",
    "billCity": "",
    "billState": "37",
    "billPin": "518176",
    "supplyCode": "37",
    "reference": "303",
    "checkIn": "2026-04-27",
    "checkInTime": "05:00",
    "checkOut": "2026-04-27",
    "checkOutTime": "19:00",
    "items": [
      {
        "id": "moh7dcmzcfv34",
        "description": "ROOM SERVICE",
        "sac": "996322",
        "rate": 1000,
        "qty": 1,
        "unit": "DAY",
        "taxRate": 5
      }
    ],
    "notes": "",
    "status": "draft",
    "total": 1050
  },
  {
    "id": "moh70kwr5ev8g",
    "invoiceNo": "INV-428",
    "customerName": "S JAMUNA BAY",
    "customerCompany": "Union Bank of India krishna Rao pet branch",
    "customerGstin": "37AAACU0564G2ZF",
    "customerPhone": "8897836864",
    "customerEmail": "",
    "billAddr1": "",
    "billAddr2": "",
    "billCity": "",
    "billState": "37",
    "billPin": "",
    "supplyCode": "37",
    "reference": "303",
    "checkIn": "2026-04-27",
    "checkInTime": "05:00",
    "checkOut": "2026-04-27",
    "checkOutTime": "19:00",
    "items": [
      {
        "id": "moh70kwsznzqe",
        "description": "ROOM SERVICE",
        "sac": "996322",
        "rate": 1000,
        "qty": 1,
        "unit": "DAY",
        "taxRate": 5
      }
    ],
    "notes": "",
    "status": "draft",
    "total": 1050
  },
  {
    "id": "moh236m1765mk",
    "invoiceNo": "INV-427",
    "customerName": "CH SREENIVASULU",
    "customerCompany": "Union Bank of India  Nandyal main branch",
    "customerGstin": "37AaaCU0564G2ZF",
    "customerPhone": "9182405497",
    "customerEmail": "",
    "billAddr1": "",
    "billAddr2": "",
    "billCity": "Nandyal",
    "billState": "37",
    "billPin": "518501",
    "supplyCode": "37",
    "reference": "207",
    "checkIn": "2026-04-27",
    "checkInTime": "05:00",
    "checkOut": "2026-04-27",
    "checkOutTime": "16:31",
    "items": [
      {
        "id": "moh236m1adojs",
        "description": "ROOM SERVICE",
        "sac": "996322",
        "rate": 1000,
        "qty": 1,
        "unit": "DAY",
        "taxRate": 5
      }
    ],
    "notes": "",
    "status": "draft",
    "total": 1050
  },
  {
    "id": "moh1lxr60micu",
    "invoiceNo": "INV-426",
    "customerName": "p SRINIVASULU",
    "customerCompany": "UNION Bank of India NOONE PALLI NANDYAL 518501",
    "customerGstin": "37AAACU0564G2ZF",
    "customerPhone": "9701605406",
    "customerEmail": "",
    "billAddr1": "",
    "billAddr2": "",
    "billCity": "Nandyal",
    "billState": "37",
    "billPin": "510501",
    "supplyCode": "37",
    "reference": "208",
    "checkIn": "2026-04-27",
    "checkInTime": "05:00",
    "checkOut": "2026-04-27",
    "checkOutTime": "16:30",
    "items": [
      {
        "id": "moh1lxr61d561",
        "description": "ROOM SERVICE",
        "sac": "996322",
        "rate": 1000,
        "qty": 1,
        "unit": "DAY",
        "taxRate": 5
      }
    ],
    "notes": "",
    "status": "draft",
    "total": 1050
  },
  {
    "id": "mo8aos0zan2ug",
    "invoiceNo": "INV-425",
    "customerName": "Prathap",
    "customerCompany": "",
    "customerGstin": "",
    "customerPhone": "",
    "customerEmail": "",
    "billAddr1": "",
    "billAddr2": "",
    "billCity": "",
    "billState": "37",
    "billPin": "",
    "supplyCode": "37",
    "reference": "102",
    "checkIn": "2026-04-20",
    "checkInTime": "17:26",
    "checkOut": "2026-04-22",
    "checkOutTime": "06:00",
    "items": [
      {
        "id": "mo8aos0zxz97d",
        "description": "ROOM SERVICE",
        "sac": "996322",
        "rate": 2500,
        "qty": 2,
        "unit": "DAY",
        "taxRate": 5
      }
    ],
    "notes": "",
    "status": "draft",
    "total": 5250
  }
]