[
  {
    "id": "mo6vy9jm78u62",
    "invoiceNo": "INV-426",
    "customerName": "Bhoopal Reddy Y",
    "customerCompany": "",
    "customerGstin": "",
    "customerPhone": "",
    "customerEmail": "bhupal181111@gmail.com",
    "billAddr1": "",
    "billAddr2": "",
    "billCity": "",
    "billState": "37",
    "billPin": "",
    "supplyCode": "37",
    "reference": "",
    "checkIn": "2026-04-19",
    "checkInTime": "12:00",
    "checkOut": "2026-04-21",
    "checkOutTime": "11:00",
    "items": [
      {
        "id": "mo6vy9jm1ntvg",
        "description": "ROOM SERVICE",
        "sac": "996322",
        "rate": 1200,
        "qty": 2,
        "unit": "DAY",
        "taxRate": 5
      }
    ],
    "notes": "",
    "status": "draft",
    "total": 2520
  }
]